{"inkVersion":21,"root":[["\n","#","^speaker:Narrator ","/#","#","^layout:Right","/#","ev",{"VAR?":"PlayerName"},"str","^","/str","==","/ev",[{"->":".^.b","c":true},{"b":["^ ",{"->":"main"},{"->":"0.16"},null]}],[{"->":".^.b"},{"b":["^ ",{"->":"alreadyChosen"},{"->":"0.16"},null]}],"nop","\n",["done",{"#f":5,"#n":"g-0"}],null],"done",{"main":[["^This is the start of this story.","\n","^It's a very good story.","\n","^So once upon a time there was a...","\n","^I forgot, can you remind me who you are?","\n","ev","str","^a princess in a tower","/str","/ev",{"*":".^.c-0","flg":20},"ev","str","^a man who got reincarnated as a slime","/str","/ev",{"*":".^.c-1","flg":20},"ev","str","^a girl who got chased by her ancestor for a ritual","/str","/ev",{"*":".^.c-2","flg":20},{"c-0":["\n","ev","str","^Rapunzel","/str","/ev",{"->":"chosen"},{"#f":5}],"c-1":["\n","ev","str","^Rimuru","/str","/ev",{"->":"chosen"},{"#f":5}],"c-2":["\n","ev","str","^Stella","/str","/ev",{"->":"chosen"},{"#f":5}]}],{"#f":1}],"chosen":[{"temp=":"choice"},"^Ah right right, ","ev",{"VAR?":"choice"},"out","/ev","^. how could I forget.","\n","ev",{"VAR?":"choice"},"/ev",{"VAR=":"PlayerName","re":true},"^The story hasn't ended yet, go on and write the rest.","\n","end",{"#f":1}],"alreadyChosen":["^Hi ","ev",{"VAR?":"PlayerName"},"out","/ev","^, I'm sorry I'm quite busy right now.","\n","^Could you come back later?","\n","end",{"#f":1}],"global decl":["ev","str","^","/str",{"VAR=":"PlayerName"},"/ev","end",null],"#f":1}],"listDefs":{}}